{"id":4,"date":"2018-03-30T10:27:15","date_gmt":"2018-03-30T10:27:15","guid":{"rendered":"http:\/\/rarathemesdemo.com\/education-zone-pro\/newsletter\/"},"modified":"2018-03-30T10:27:15","modified_gmt":"2018-03-30T10:27:15","slug":"newsletter-2","status":"publish","type":"page","link":"https:\/\/www.sramps.sch.ae\/newsletter-2\/","title":{"rendered":"Newsletter"},"content":{"rendered":"<div class=\"tnp tnp-subscription \">\n<form method=\"post\" action=\"https:\/\/www.sramps.sch.ae\/wp-admin\/admin-ajax.php?action=tnp&amp;na=s\">\n<input type=\"hidden\" name=\"nlang\" value=\"\">\n<div class=\"tnp-field tnp-field-email\"><label for=\"tnp-1\">Email<\/label>\n<input class=\"tnp-email\" type=\"email\" name=\"ne\" id=\"tnp-1\" value=\"\" placeholder=\"\" required><\/div>\n<div class=\"tnp-field tnp-field-button\" style=\"text-align: left\"><input class=\"tnp-submit\" type=\"submit\" value=\"Subscribe\" style=\"\">\n<\/div>\n<\/form>\n<\/div>\n\n","protected":false},"excerpt":{"rendered":"","protected":false},"author":1,"featured_media":0,"parent":0,"menu_order":0,"comment_status":"closed","ping_status":"closed","template":"","meta":{"om_disable_all_campaigns":false,"_monsterinsights_skip_tracking":false,"_monsterinsights_sitenote_active":false,"_monsterinsights_sitenote_note":"","_monsterinsights_sitenote_category":0,"_uf_show_specific_survey":0,"_uf_disable_surveys":false,"footnotes":""},"class_list":["post-4","page","type-page","status-publish","hentry","latest_post"],"aioseo_notices":[],"_links":{"self":[{"href":"https:\/\/www.sramps.sch.ae\/wp-json\/wp\/v2\/pages\/4","targetHints":{"allow":["GET"]}}],"collection":[{"href":"https:\/\/www.sramps.sch.ae\/wp-json\/wp\/v2\/pages"}],"about":[{"href":"https:\/\/www.sramps.sch.ae\/wp-json\/wp\/v2\/types\/page"}],"author":[{"embeddable":true,"href":"https:\/\/www.sramps.sch.ae\/wp-json\/wp\/v2\/users\/1"}],"replies":[{"embeddable":true,"href":"https:\/\/www.sramps.sch.ae\/wp-json\/wp\/v2\/comments?post=4"}],"version-history":[{"count":0,"href":"https:\/\/www.sramps.sch.ae\/wp-json\/wp\/v2\/pages\/4\/revisions"}],"wp:attachment":[{"href":"https:\/\/www.sramps.sch.ae\/wp-json\/wp\/v2\/media?parent=4"}],"curies":[{"name":"wp","href":"https:\/\/api.w.org\/{rel}","templated":true}]}}